propan/__about__.py
propan/__init__.py
propan/__main__.py
propan/_compat.py
propan/annotations.py
propan/py.typed
propan/types.py
propan/asyncapi/__init__.py
propan/asyncapi/channels.py
propan/asyncapi/info.py
propan/asyncapi/main.py
propan/asyncapi/message.py
propan/asyncapi/security.py
propan/asyncapi/servers.py
propan/asyncapi/subscription.py
propan/asyncapi/utils.py
propan/asyncapi/bindings/__init__.py
propan/asyncapi/bindings/amqp.py
propan/asyncapi/bindings/kafka.py
propan/asyncapi/bindings/main.py
propan/asyncapi/bindings/nats.py
propan/asyncapi/bindings/redis.py
propan/asyncapi/bindings/sqs.py
propan/brokers/__init__.py
propan/brokers/constants.py
propan/brokers/exceptions.py
propan/brokers/middlewares.py
propan/brokers/push_back_watcher.py
propan/brokers/_model/__init__.py
propan/brokers/_model/broker_usecase.py
propan/brokers/_model/routing.py
propan/brokers/_model/schemas.py
propan/brokers/_model/utils.py
propan/brokers/kafka/__init__.py
propan/brokers/kafka/kafka_broker.py
propan/brokers/kafka/kafka_broker.pyi
propan/brokers/kafka/routing.py
propan/brokers/kafka/routing.pyi
propan/brokers/kafka/schemas.py
propan/brokers/nats/__init__.py
propan/brokers/nats/consts.py
propan/brokers/nats/nats_broker.py
propan/brokers/nats/nats_broker.pyi
propan/brokers/nats/nats_js_broker.py
propan/brokers/nats/nats_js_broker.pyi
propan/brokers/nats/routing.py
propan/brokers/nats/routing.pyi
propan/brokers/nats/schemas.py
propan/brokers/rabbit/__init__.py
propan/brokers/rabbit/logging.py
propan/brokers/rabbit/rabbit_broker.py
propan/brokers/rabbit/rabbit_broker.pyi
propan/brokers/rabbit/routing.py
propan/brokers/rabbit/routing.pyi
propan/brokers/rabbit/schemas.py
propan/brokers/rabbit/utils.py
propan/brokers/redis/__init__.py
propan/brokers/redis/redis_broker.py
propan/brokers/redis/redis_broker.pyi
propan/brokers/redis/routing.py
propan/brokers/redis/routing.pyi
propan/brokers/redis/schemas.py
propan/brokers/sqs/__init__.py
propan/brokers/sqs/routing.py
propan-0.1.5.26.dist-info/METADATA
propan-0.1.5.26.dist-info/WHEEL
propan-0.1.5.26.dist-info/entry_points.txt
propan-0.1.5.26.dist-info/licenses/LICENSE
propan-0.1.5.26.dist-info/RECORD
