Metadata-Version: 2.1
Name: propan
Version: 0.1.5.26
Summary: Propan framework: the simplest way to work with a messaging queues
Project-URL: Homepage, https://lancetnik.github.io/Propan/
Project-URL: Documentation, https://lancetnik.github.io/Propan/
Project-URL: Tracker, https://github.com/Lancetnik/Propan/issues
Project-URL: Source, https://github.com/Lancetnik/Propan
Author-email: Pastukhov Nikita <diementros@yandex.ru>
License-File: LICENSE
Keywords: framework,kafka,message brokers,nats,rabbitmq,redis,sqs
Classifier: Development Status :: 5 - Production/Stable
Classifier: Environment :: Web Environment
Classifier: Framework :: AsyncIO
Classifier: Framework :: Pydantic
Classifier: Framework :: Pydantic :: 1
Classifier: Framework :: Pydantic :: 2
Classifier: Intended Audience :: Developers
Classifier: Intended Audience :: Information Technology
Classifier: Intended Audience :: System Administrators
Classifier: License :: OSI Approved :: MIT License
Classifier: Operating System :: OS Independent
Classifier: Programming Language :: Python
Classifier: Programming Language :: Python :: 3
Classifier: Programming Language :: Python :: 3 :: Only
Classifier: Programming Language :: Python :: 3.8
Classifier: Programming Language :: Python :: 3.9
Classifier: Programming Language :: Python :: 3.10
Classifier: Programming Language :: Python :: 3.11
Classifier: Programming Language :: Python :: 3.12
Classifier: Programming Language :: Python :: Implementation :: CPython
Classifier: Topic :: Internet
Classifier: Topic :: Software Development
Classifier: Topic :: Software Development :: Libraries
Classifier: Topic :: Software Development :: Libraries :: Application Frameworks
Classifier: Topic :: Software Development :: Libraries :: Python Modules
Classifier: Typing :: Typed
Requires-Python: >=3.8
Requires-Dist: fast-depends<2.2.0,>=2.1.1
Requires-Dist: typer
Requires-Dist: uvloop!=0.15.0,!=0.15.1,>=0.14.0; sys_platform != 'win32' and (sys_platform != 'cygwin' and platform_python_implementation != 'PyPy')
Requires-Dist: watchfiles
Provides-Extra: async-kafka
Requires-Dist: aiokafka<0.10,>=0.9; extra == 'async-kafka'
Provides-Extra: async-nats
Requires-Dist: nats-py!=2.3.0,>=2; extra == 'async-nats'
Provides-Extra: async-rabbit
Requires-Dist: aio-pika>=9; extra == 'async-rabbit'
Provides-Extra: async-redis
Requires-Dist: redis>=4.2.0rc1; extra == 'async-redis'
Provides-Extra: async-sqs
Requires-Dist: aiobotocore; extra == 'async-sqs'
Provides-Extra: doc
Requires-Dist: email-validator>=2.0.0; extra == 'doc'
Requires-Dist: fastapi; extra == 'doc'
Requires-Dist: jsonref; extra == 'doc'
Requires-Dist: polyfactory>=2.5.0; extra == 'doc'
Requires-Dist: pyyaml; extra == 'doc'
Requires-Dist: uvicorn; extra == 'doc'
